slogpy/__init__.py
slogpy/__main__.py
slogpy/progress.py
slogpy/section.py
slogpy/slog.py
slogpy/syslogger.py
slogpy/util.py
slogpy-0.1.0.dev0.dist-info/LICENSE
slogpy-0.1.0.dev0.dist-info/METADATA
slogpy-0.1.0.dev0.dist-info/WHEEL
slogpy-0.1.0.dev0.dist-info/RECORD
