Metadata-Version: 2.1
Name: slogpy
Version: 0.1.0.dev0
Summary: Basic console and file logging
Home-page: https://github.com/slogpy/slogpy
License: LICENSE
Author: Neel Malik
Author-email: n33lm@outlook.com
Requires-Python: >=3.8,<4.0
Classifier: Environment :: Console
Classifier: License :: Other/Proprietary License
Classifier: Programming Language :: Python :: 3
Classifier: Programming Language :: Python :: 3.8
Classifier: Programming Language :: Python :: 3.9
Classifier: Programming Language :: Python :: 3.10
Classifier: Programming Language :: Python :: 3.11
Classifier: Programming Language :: Python :: 3.12
Classifier: Topic :: Software Development :: Libraries :: Python Modules
Requires-Dist: rich (>=13.7.0,<14.0.0)
Project-URL: Repository, https://github.com/slogpy/slogpy
